[
  {
    "type": "intro",
    "label": "Lorem ipsum dolor sit amet, consectetur adipiscing elit. Morbi pulvinar elit in tellus posuere, eu congue neque interdum. Pellentesque habitant morbi tristique senectus et netus et malesuada fames ac turpis egestas. Aenean consectetur iaculis libero nec efficitur. Integer nec volutpat justo, non bibendum arcu. "
  },
  {
    "label": "Lorem ipsum dolor sit amet, consectetur adipiscing elit?",
    "answers": [
      { "label": "Fusce nunc nunc, pharetra eget sem et." },
      { "label": "Etiam aliquet diam et porttitor finibus." },
      {
        "label": "Maecenas commodo erat id elit aliquet, eu tempus orci lobortis."
      }
    ]
  },
  {
    "label": "Aliquam interdum tincidunt eleifend?",
    "answers": [
      { "label": "Praesent at ante egestas, efficitur ante lobortis." },
      { "label": "Morbi ultricies mauris ac massa malesuada." },
      {
        "label": "Phasellus urna risus, vehicula nec nisi vel."
      }
    ]
  }
]
